MANIFEST.in
README.md
VERSION
requirements.txt
setup.cfg
setup.py
rhasspy_speakers_cli_hermes.egg-info/PKG-INFO
rhasspy_speakers_cli_hermes.egg-info/SOURCES.txt
rhasspy_speakers_cli_hermes.egg-info/dependency_links.txt
rhasspy_speakers_cli_hermes.egg-info/entry_points.txt
rhasspy_speakers_cli_hermes.egg-info/requires.txt
rhasspy_speakers_cli_hermes.egg-info/top_level.txt
rhasspyspeakers_cli_hermes/__init__.py
rhasspyspeakers_cli_hermes/__main__.py